mr_clean/__init__.py
mr_clean/_utils/__init__.py
mr_clean/_utils/data_handling.py
mr_clean/_utils/globals.py
mr_clean/_utils/io.py
mr_clean/_utils/substrings/__init__.py
mr_clean/_utils/substrings/substr_list.py
mr_clean/_utils/substrings/substr_main.py
mr_clean/_utils/substrings/suffix_tree.py
mr_clean/core/__init__.py
mr_clean/core/api.py
mr_clean/core/functions/__init__.py
mr_clean/core/functions/basics.py
mr_clean/core/functions/colnames.py
mr_clean/core/functions/scrub.py
mr_clean/core/stats/__init__.py
mr_clean/core/stats/regression.py
mr_clean/core/stats/summary.py
mr_clean/core/stats/transform.py
mr_clean/core/tools/__init__.py
mr_clean/core/tools/cleaner.py
mr_clean/core/tools/diagnose.py
mr_clean/core/tools/mrc.py
mr_clean/core/tools/summarize.py
mr_clean-0.0.8.dist-info/LICENSE
mr_clean-0.0.8.dist-info/METADATA
mr_clean-0.0.8.dist-info/WHEEL
mr_clean-0.0.8.dist-info/top_level.txt
mr_clean-0.0.8.dist-info/RECORD
