Metadata-Version: 2.1
Name: mr-clean
Version: 0.0.8
Summary: A small package for cleaning data.
Home-page: https://github.com/a1liu/mr_clean
Author: A1Liu
Author-email: albertymliu@gmail.com
License: UNKNOWN
Platform: UNKNOWN
Classifier: Programming Language :: Python :: 3
Classifier: License :: OSI Approved :: GNU General Public License (GPL)
Classifier: Operating System :: OS Independent
Requires-Dist: pandas
Requires-Dist: numpy
Requires-Dist: anytree
